recon_wake/__init__.py
recon_wake/__main__.py
recon_wake/py.typed
recon_wake/server.py
recon_wake/contracts/MockERC20.sol
recon_wake-0.2.0.dist-info/licenses/LICENSE
recon_wake-0.2.0.dist-info/METADATA
recon_wake-0.2.0.dist-info/WHEEL
recon_wake-0.2.0.dist-info/entry_points.txt
recon_wake-0.2.0.dist-info/top_level.txt
recon_wake-0.2.0.dist-info/RECORD
