Metadata-Version: 2.4
Name: recon-wake
Version: 0.2.0
Summary: MCP server for Wake testing framework and Certora formal verification
Author-email: Your Name <terabase7@gmail.com>
License: MIT
Project-URL: Homepage, https://github.com/Recon-Fuzz/recon-wake-mcp
Project-URL: Repository, https://github.com/Recon-Fuzz/recon-wake-mcp
Project-URL: Issues, https://github.com/Recon-Fuzz/recon-wake-mcp/issues
Keywords: wake,solidity,testing,mcp,ethereum,smart-contracts,certora,formal-verification,cvl
Classifier: Development Status :: 4 - Beta
Classifier: Intended Audience :: Developers
Classifier: License :: OSI Approved :: MIT License
Classifier: Programming Language :: Python :: 3
Classifier: Programming Language :: Python :: 3.9
Classifier: Programming Language :: Python :: 3.10
Classifier: Programming Language :: Python :: 3.11
Classifier: Programming Language :: Python :: 3.12
Classifier: Topic :: Software Development :: Testing
Requires-Python: >=3.9
License-File: LICENSE
Requires-Dist: eth-wake>=4.0.0
Requires-Dist: fastmcp>=0.1.0
Requires-Dist: certora-cli>=8.0.0
Dynamic: license-file
